MANIFEST.in
README.md
setup.cfg
setup.py
example/__init__.py
example/flask_app.py
profiler/__init__.py
profiler/add_headers.py
profiler/profile_manager.py
server_timing_profiler.egg-info/PKG-INFO
server_timing_profiler.egg-info/SOURCES.txt
server_timing_profiler.egg-info/dependency_links.txt
server_timing_profiler.egg-info/entry_points.txt
server_timing_profiler.egg-info/namespace_packages.txt
server_timing_profiler.egg-info/requires.txt
server_timing_profiler.egg-info/top_level.txt