Metadata-Version: 1.1
Name: server-timing-profiler
Version: 0.0.2
Summary: HTTP Server-Timing for Python Flask
Home-page: https://github.com/PammyS/server-timing-profiler
Author: Perminder Singh
Author-email: svicky9797@gmail.com
License: Apache License 2.0
Keywords: HTTP Server-Timing for Python Flask
Platform: Linux
Platform: POSIX
Classifier: Programming Language :: Python :: 2.7
